tests/__init__.py
tests/conftest.py
tests/constants.py
tests/utils.py
tests/functional/__init__.py
tests/functional/test_async_to_sync.py
tests/functional/test_pydantic_v1.py
tests/functional/codegen/__init__.py
tests/functional/codegen/test_codegen.py
tests/functional/multiple_servers/__init__.py
tests/functional/multiple_servers/client_inside_server_test.py
tests/functional/multiple_servers/conftest.py
tests/functional/multiple_servers/multiple_clients_test.py
tests/functional/multiple_servers/server1.py
tests/functional/multiple_servers/server2.py
tests/functional/single_server/__init__.py
tests/functional/single_server/client_generation_test.py
tests/functional/single_server/client_server_test.py
tests/functional/single_server/client_test.py
tests/functional/single_server/conftest.py
tests/functional/single_server/register_rpc_test.py
tests/functional/single_server/server.py
tests/functional/single_server/server_test.py
tests/functional/single_server/tcp_client_generation_test.py
tests/functional/single_server/tcp_client_test.py
tests/functional/single_server/tcp_server.py
tests/functional/single_server/threaded_server.py
tests/unit/__init__.py
tests/unit/test_server.py
tests/unit/utils/__init__.py
tests/unit/utils/test_type_util.py
tests/unit/utils/test_util.py
tests/unit/zeromq_patterns/__init__.py
tests/unit/zeromq_patterns/test_zeromq_worker.py
zero/__init__.py
zero/config.py
zero/error.py
zero/generate_client.py
zero/logger.py
zero/codegen/__init__.py
zero/codegen/codegen.py
zero/encoder/__init__.py
zero/encoder/generic.py
zero/encoder/msgspc.py
zero/encoder/protocols.py
zero/protocols/__init__.py
zero/protocols/blueprint.py
zero/protocols/common_rpc.py
zero/protocols/tcp/__init__.py
zero/protocols/tcp/client.py
zero/protocols/tcp/frame_io.py
zero/protocols/tcp/server.py
zero/protocols/tcp/worker.py
zero/protocols/zeromq/__init__.py
zero/protocols/zeromq/client.py
zero/protocols/zeromq/server.py
zero/protocols/zeromq/worker.py
zero/pubsub/__init__.py
zeroapi-1.0.1.dist-info/licenses/LICENSE
zeroapi-1.0.1.dist-info/METADATA
zeroapi-1.0.1.dist-info/WHEEL
zeroapi-1.0.1.dist-info/top_level.txt
zeroapi-1.0.1.dist-info/RECORD
