Metadata-Version: 2.4
Name: zeroapi
Version: 1.0.1
Summary: Zero is a simple and fast Python RPC framework
Home-page: https://github.com/Ananto30/zero
Author: Azizul Haque Ananto
Author-email: azizulhaq.ananto@gmail.com
License: MIT
Classifier: Programming Language :: Python :: 3
Classifier: License :: OSI Approved :: MIT License
Classifier: Operating System :: OS Independent
Requires-Python: >=3.9
License-File: LICENSE
Requires-Dist: pyzmq
Requires-Dist: msgspec
Provides-Extra: pydantic
Requires-Dist: pydantic; extra == "pydantic"
Provides-Extra: uvloop
Requires-Dist: uvloop; extra == "uvloop"
Provides-Extra: tornado
Requires-Dist: tornado; extra == "tornado"
Provides-Extra: all
Requires-Dist: pydantic; extra == "all"
Requires-Dist: uvloop; extra == "all"
Requires-Dist: tornado; extra == "all"
Dynamic: author
Dynamic: author-email
Dynamic: classifier
Dynamic: description
Dynamic: description-content-type
Dynamic: home-page
Dynamic: license
Dynamic: license-file
Dynamic: provides-extra
Dynamic: requires-dist
Dynamic: requires-python
Dynamic: summary
